{
  "updated": "15 Jul 2026 06:08 UTC",
  "total": 781,
  "severity": {
    "critical": 94,
    "high": 496,
    "medium": 170
  },
  "categories": {
    "aws": 45,
    "azure": 313,
    "gcp": 1,
    "general": 422
  },
  "top_critical": {
    "title": "Joomla Extensions CVSSv3 10.0 Flaws Exploited in Wild",
    "summary": "Attackers are actively exploiting critical vulnerabilities (CVSS 10.0) in two popular Joomla extensions \u2014 iCagenda and Balbooa Forms \u2014 to compromise websites running the open-source CMS. Joomla powers",
    "architects_take": "If your organisation hosts or manages any Joomla-based sites, audit installed extensions immediately and apply patches for iCagenda and Balbooa Forms without delay. Where immediate patching isn't possible, use a web application firewall (WAF) to block exploit attempts and consider temporarily disabling the affected extensions until remediation is confirmed.",
    "slug": "joomla-icagenda-balbooa-forms-critical-cvss10-exploitation",
    "source": "The Register \u2014 Security",
    "category": "general"
  }
}